concretedesignpy/__init__.py
concretedesignpy/general.py
concretedesignpy/provision.py
concretedesignpy/beam/__init__.py
concretedesignpy/beam/moment_capacity.py
concretedesignpy/beam/shear_capacity.py
concretedesignpy/crfp/__init__.py
concretedesignpy/crfp/column.py
concretedesignpy/crfp/constants.py
concretedesignpy/crfp/flexure.py
concretedesignpy/mgt/__init__.py
concretedesignpy/mgt/fiber.py
concretedesignpy/stress-strain/__init__.py
concretedesignpy/stress-strain/manders.py
concretedesignpy-0.2.dist-info/METADATA
concretedesignpy-0.2.dist-info/WHEEL
concretedesignpy-0.2.dist-info/top_level.txt
concretedesignpy-0.2.dist-info/RECORD
