Metadata-Version: 2.2
Name: concretedesignpy
Version: 0.2
Summary: This APEC internal use only for Concrete Design using ACI and NSCP
Home-page: https://github.com/albertp16/apec-py
Author: Albert Pamonag
Author-email: albert@apeconsultancy.net
Classifier: Programming Language :: Python :: 3
Classifier: Operating System :: OS Independent
Requires-Dist: matplotlib
Dynamic: author
Dynamic: author-email
Dynamic: classifier
Dynamic: home-page
Dynamic: requires-dist
Dynamic: summary
